bactinspector/__init__.py
bactinspector/commands.py
bactinspector/dataframe_parsing_functions.py
bactinspector/mash_functions.py
bactinspector/run_bactinspector.py
bactinspector/utility_functions.py
bactinspector/data/all_complete_bacteria_refseq.k21s1000.msh
bactinspector/data/all_complete_bacteria_refseq.k21s1000.species.distance_and_length_metrics.tsv
bactinspector/data/all_complete_bacteria_refseq.k21s1000.species.tsv
BactInspectorMax-0.1.3.dist-info/METADATA
BactInspectorMax-0.1.3.dist-info/WHEEL
BactInspectorMax-0.1.3.dist-info/entry_points.txt
BactInspectorMax-0.1.3.dist-info/top_level.txt
BactInspectorMax-0.1.3.dist-info/RECORD
