Metadata-Version: 2.1
Name: BactInspectorMax
Version: 0.1.3
Summary: Package to investigate mash hits against refseq
Home-page: UNKNOWN
Author: Anthony Underwood
Author-email: au3@sanger.ac.uk
License: MIT
Platform: UNKNOWN
Classifier: Development Status :: 3 - Alpha
Classifier: Intended Audience :: Science/Research
Classifier: License :: OSI Approved :: MIT License
Classifier: Programming Language :: Python :: 3
Requires-Dist: pandas
Requires-Dist: numpy
